iconconsole/__init__.py
iconconsole/account.py
iconconsole/network.py
iconconsole/score.py
iconconsole/transaction.py
iconconsole/base/__init__.py
iconconsole/base/address.py
iconconsole/base/exception.py
iconconsole/typing/__init__.py
iconconsole/utils/__init__.py
iconconsole-0.1.1.dist-info/LICENSE
iconconsole-0.1.1.dist-info/METADATA
iconconsole-0.1.1.dist-info/WHEEL
iconconsole-0.1.1.dist-info/top_level.txt
iconconsole-0.1.1.dist-info/RECORD
