Metadata-Version: 2.1
Name: iconconsole
Version: 0.1.1
Summary: package to interact with ICON network.
Home-page: https://github.com/eunsoo-icon/icon-console
Author: Park Eunsoo
Author-email: eunsoo.park@gmail.com
License: Apache License 2.0
Platform: UNKNOWN
Classifier: Development Status :: 5 - Production/Stable
Classifier: Intended Audience :: Developers
Classifier: Natural Language :: English
Classifier: License :: OSI Approved :: Apache Software License
Classifier: Programming Language :: Python :: 3.7
Requires-Python: ~=3.7
License-File: LICENSE
Requires-Dist: iconsdk
Provides-Extra: tests
Requires-Dist: pytest (~=6.2.5) ; extra == 'tests'
